MANIFEST.in
README.md
setup.cfg
setup.py
dismake/__init__.py
dismake/asset.py
dismake/cli.py
dismake/client.py
dismake/commands.py
dismake/enums.py
dismake/errors.py
dismake/flags.py
dismake/handler.py
dismake/http.py
dismake/params.py
dismake/permissions.py
dismake/plugin.py
dismake/utils.py
dismake.egg-info/PKG-INFO
dismake.egg-info/SOURCES.txt
dismake.egg-info/dependency_links.txt
dismake.egg-info/entry_points.txt
dismake.egg-info/requires.txt
dismake.egg-info/top_level.txt
dismake/models/__init__.py
dismake/models/application_command.py
dismake/models/channels.py
dismake/models/components.py
dismake/models/embed.py
dismake/models/emoji.py
dismake/models/guild.py
dismake/models/interaction.py
dismake/models/message.py
dismake/models/permission_overwrites.py
dismake/models/role.py
dismake/models/user.py
dismake/templates/main.py
dismake/templates/requirements.txt
dismake/ui/__init__.py
dismake/ui/button.py
dismake/ui/component.py
dismake/ui/modal.py
dismake/ui/select.py
dismake/ui/view.py
test/tests.py