Metadata-Version: 2.1
Name: dismake
Version: 0.0.21
Summary: None
Home-page: https://github.com/Apptic-Development/dismake
Author: Pranoy Majumdar
Author-email: officialpranoy2@gmail.com
License: MIT
Project-URL: Homepage, https://github.com/Apptic-Development/dismake
Platform: UNKNOWN
Classifier: Development Status :: 2 - Pre-Alpha
Classifier: License :: OSI Approved :: MIT License
Classifier: Intended Audience :: Developers
Classifier: Natural Language :: English
Classifier: Operating System :: OS Independent
Classifier: Programming Language :: Python :: 3.9
Classifier: Programming Language :: Python :: 3.10
Classifier: Programming Language :: Python :: 3.11
Classifier: Topic :: Internet
Classifier: Topic :: Software Development :: Libraries
Classifier: Topic :: Software Development :: Libraries :: Python Modules
Classifier: Topic :: Utilities
Classifier: Typing :: Typed
Requires-Python: >=3.9
